<?xml version='1.0' encoding='utf-8' ?>
<!DOCTYPE book PUBLIC "-//OASIS//DTD DocBook XML V4.5//EN" "http://www.oasis-open.org/docbook/xml/4.5/docbookx.dtd" [
<!ENTITY % BOOK_ENTITIES SYSTEM "../Drools_Guvnor.ent">
%BOOK_ENTITIES;
]>
<part>
   <title>Administration Guide</title>

   <partintro>
      <para>
      This part covers installation and administration issues of the Guvnor.
      </para>
      <para>
      The Guvnor is a web application that can run in multiple environments, and be configured to suit most
      situations. There is also some initial setup of data, and export/import functions covered.
      </para>
   </partintro>

  <xi:include href="Chapter-Installation.xml" xmlns:xi="http://www.w3.org/2001/XInclude"/>
  <xi:include href="Chapter-Database_config.xml" xmlns:xi="http://www.w3.org/2001/XInclude"/>
  
</part>